minspect/__about__.py
minspect/__init__.py
minspect/inspecting.py
minspect/main.py
minspect/tests/test_main.py
minspect-0.0.8.dist-info/METADATA
minspect-0.0.8.dist-info/WHEEL
minspect-0.0.8.dist-info/entry_points.txt
minspect-0.0.8.dist-info/licenses/LICENSE
minspect-0.0.8.dist-info/RECORD
